LICENSE
README.md
setup.cfg
setup.py
tests/__init__.py
tests/test_neo4j_loader.py
wilhelm_graphdb_python/__init__.py
wilhelm_graphdb_python/neo4j_loader.py
wilhelm_graphdb_python.egg-info/PKG-INFO
wilhelm_graphdb_python.egg-info/SOURCES.txt
wilhelm_graphdb_python.egg-info/dependency_links.txt
wilhelm_graphdb_python.egg-info/not-zip-safe
wilhelm_graphdb_python.egg-info/requires.txt
wilhelm_graphdb_python.egg-info/top_level.txt