Metadata-Version: 2.1
Name: wilhelm-graphdb-python
Version: 0.0.10
Summary: A package suitable for offline vocabulary processing and batch ingestion into Graph databases, such as Neo4j and ArangoDB
Home-page: https://github.com/QubitPi/wilhelm-graphdb-python
Author: Jiaqi (Hutao of Emberfire)
Author-email: jack20220723@gmail.com
License: Apache-2.0
Requires-Python: >=3.10
License-File: LICENSE
